ChaseOaksAssignment10/__init__.py
ChaseOaksAssignment10/main.py
ChaseOaksAssignment10-0.0.5.dist-info/METADATA
ChaseOaksAssignment10-0.0.5.dist-info/WHEEL
ChaseOaksAssignment10-0.0.5.dist-info/top_level.txt
ChaseOaksAssignment10-0.0.5.dist-info/RECORD
