Metadata-Version: 2.1
Name: ChaseOaksAssignment10
Version: 0.0.5
Summary: Assignment10
Author: Chase Oaks
Author-email: <chaseoaks14@gmail.com>
Keywords: python,Assignment10
Classifier: Development Status :: 3 - Alpha
Classifier: Intended Audience :: Education
Classifier: Programming Language :: Python :: 2
Classifier: Programming Language :: Python :: 3
Classifier: Operating System :: MacOS :: MacOS X
Classifier: Operating System :: Microsoft :: Windows
